AB_library/__init__.py
AB_library/ab_testing.py
AB_library-0.2.5.dist-info/LICENSE
AB_library-0.2.5.dist-info/METADATA
AB_library-0.2.5.dist-info/WHEEL
AB_library-0.2.5.dist-info/top_level.txt
AB_library-0.2.5.dist-info/RECORD
