Metadata-Version: 2.1
Name: AB-library
Version: 0.2.5
Summary: A comprehensive Python library for A/B testing analysis
Home-page: https://github.com/Renarion/AB_library
Author: Renat/Egor
Author-email: ryunisov0@gmail.com
License: UNKNOWN
Platform: UNKNOWN
Classifier: Intended Audience :: Science/Research
Classifier: Topic :: Software Development :: Libraries
Classifier: License :: OSI Approved :: MIT License
Classifier: Programming Language :: Python :: 3
Classifier: Programming Language :: Python :: 3.7
Classifier: Programming Language :: Python :: 3.8
Classifier: Programming Language :: Python :: 3.9
Classifier: Programming Language :: Python :: 3.10
Classifier: Programming Language :: Python :: 3.11
Classifier: Programming Language :: Python :: 3.12
License-File: LICENSE
Requires-Dist: numpy (>=1.18.0)
Requires-Dist: pandas (>=1.0.0)
Requires-Dist: matplotlib (>=3.0.0)
Requires-Dist: scipy (>=1.4.0)
Requires-Dist: statsmodels (>=0.12.0)
Requires-Dist: seaborn (>=0.11.0)
Requires-Dist: tqdm (>=4.0.0)
